sen2classification/__init__.py
sen2classification/alcc.py
sen2classification/bands.py
sen2classification/exceptions.py
sen2classification/gb_classification.py
sen2classification/helpers.py
sen2classification/land_cover_classification.py
sen2classification/metas.py
sen2classification/product.py
sen2classification/spectral_index.py
sen2classification-0.0.1.dist-info/METADATA
sen2classification-0.0.1.dist-info/WHEEL
sen2classification-0.0.1.dist-info/top_level.txt
sen2classification-0.0.1.dist-info/RECORD
