Metadata-Version: 2.1
Name: sen2classification
Version: 0.0.1
Summary: Python library for automatic land cover classification of Sentinel 2 satellite images
Home-page: https://github.com/lraspovic/sen2classification
Author: Luka Raspovic
Author-email: <lraspovic993@gmail.com>
License: MIT
Keywords: python,sentinel 2,machine learning,land cover,classification,automatic,satellite,image classification
Platform: UNKNOWN
Classifier: License :: OSI Approved :: MIT License
Classifier: Programming Language :: Python :: 3
Classifier: Programming Language :: Python :: 3.8
Requires-Python: >=3.6
Requires-Dist: scikit-learn
Requires-Dist: imbalanced-learn
Requires-Dist: xgboost
